vcr_langchain/__init__.py
vcr_langchain/bash_patch.py
vcr_langchain/dummy.py
vcr_langchain/generic.py
vcr_langchain/patch.py
vcr_langchain/py.typed
vcr_langchain-0.0.31.dist-info/LICENSE
vcr_langchain-0.0.31.dist-info/METADATA
vcr_langchain-0.0.31.dist-info/WHEEL
vcr_langchain-0.0.31.dist-info/RECORD
