Metadata-Version: 2.1
Name: vcr-langchain
Version: 0.0.31
Summary: Record and replay LLM interactions for langchain
Author: Amos Jun-yeung Ng
Author-email: me@amos.ng
Requires-Python: >=3.8.1,<4.0
Classifier: Programming Language :: Python :: 3
Classifier: Programming Language :: Python :: 3.9
Classifier: Programming Language :: Python :: 3.10
Classifier: Programming Language :: Python :: 3.11
Requires-Dist: gorilla (>=0.4.0,<0.5.0)
Requires-Dist: langchain (>=0.1.0,<0.2.0)
Requires-Dist: langchain-community (>=0.0.10,<0.0.11)
Requires-Dist: langchain-openai (>=0.0.2,<0.0.3)
Requires-Dist: pydantic (>=2.5.3,<3.0.0)
Requires-Dist: vcrpy (>=4.3.1,<5.0.0)
